git_commits/__init__.py
git_commits/core.py
git_commits/py.typed
git_commits/schemas.py
git_commits/utils.py
git_commits-1.0.1.dist-info/METADATA
git_commits-1.0.1.dist-info/WHEEL
git_commits-1.0.1.dist-info/licenses/LICENSE
git_commits-1.0.1.dist-info/RECORD
