Metadata-Version: 2.4
Name: git-commits
Version: 1.0.1
Summary: A Python library for listing Git commits from local repositories with advanced filtering options
Project-URL: Homepage, https://adhikariarjun.com.np/git-commits/
Project-URL: Repository, https://github.com/thearjun/git-commits
Project-URL: Documentation, https://github.com/thearjun/git-commits#readme
Project-URL: Bug Tracker, https://github.com/thearjun/git-commits/issues
Author-email: Arjun Adhikari <mailarjunadhikari@gmail.com>
Maintainer-email: Arjun Adhikari <mailarjunadhikari@gmail.com>
License: MIT
License-File: LICENSE
Keywords: commits,git,history,repository,version-control
Classifier: Development Status :: 4 - Beta
Classifier: Intended Audience :: Developers
Classifier: License :: OSI Approved :: MIT License
Classifier: Operating System :: OS Independent
Classifier: Programming Language :: Python :: 3
Classifier: Programming Language :: Python :: 3 :: Only
Classifier: Programming Language :: Python :: 3.9
Classifier: Programming Language :: Python :: 3.10
Classifier: Programming Language :: Python :: 3.11
Classifier: Programming Language :: Python :: 3.12
Classifier: Topic :: Software Development :: Libraries :: Python Modules
Classifier: Topic :: Software Development :: Version Control :: Git
Classifier: Topic :: Utilities
Requires-Python: >=3.9
Requires-Dist: dateparser>=1.2.1
Requires-Dist: gitpython>=3.1.40
Requires-Dist: pytz>=2024.1
